moteus_gui/__init__.py
moteus_gui/tview.py
moteus_gui/tview_main_window.ui
moteus_gui/version.py
moteus_gui-0.3.98.dist-info/METADATA
moteus_gui-0.3.98.dist-info/WHEEL
moteus_gui-0.3.98.dist-info/entry_points.txt
moteus_gui-0.3.98.dist-info/top_level.txt
moteus_gui-0.3.98.dist-info/RECORD
